oc_dlinterface/__init__.py
oc_dlinterface/dlbuild_worker_interface.py
oc_dlinterface/dlupload_worker_interface.py
oc_dlinterface-1.0.0.dist-info/LICENSE
oc_dlinterface-1.0.0.dist-info/METADATA
oc_dlinterface-1.0.0.dist-info/WHEEL
oc_dlinterface-1.0.0.dist-info/top_level.txt
oc_dlinterface-1.0.0.dist-info/RECORD
