Metadata-Version: 2.1
Name: oc-dlinterface
Version: 1.0.0
Summary: dl interface
Requires-Python: >=2.7,!=3.0.*,!=3.1.*,!=3.2.*,!=3.3.*,!=3.4.*,!=3.5.*
License-File: LICENSE
Requires-Dist: oc-cdt-queue2
